sanityscan_dhruva/__init__.py
sanityscan_dhruva-0.1.0.dist-info/METADATA
sanityscan_dhruva-0.1.0.dist-info/WHEEL
sanityscan_dhruva-0.1.0.dist-info/RECORD
