Metadata-Version: 2.4
Name: sanityscan-dhruva
Version: 0.1.0
Summary: CSV sanity report + stratified train/val/test splits.
Requires-Python: >=3.8
Requires-Dist: numpy
Requires-Dist: pandas
Requires-Dist: scikit-learn
